jdDBusDebugger/Constants.py
jdDBusDebugger/Environment.py
jdDBusDebugger/Functions.py
jdDBusDebugger/Icon.png
jdDBusDebugger/__init__.py
jdDBusDebugger/__main__.py
jdDBusDebugger/version.txt
jdDBusDebugger/core/Languages.py
jdDBusDebugger/core/MacroManager.py
jdDBusDebugger/core/Server.py
jdDBusDebugger/core/Settings.py
jdDBusDebugger/core/UnixUserDatabase.py
jdDBusDebugger/core/__init__.py
jdDBusDebugger/data/changelog.html
jdDBusDebugger/data/translators.json
jdDBusDebugger/gui/AboutDialog.py
jdDBusDebugger/gui/CentralWidget.py
jdDBusDebugger/gui/ConnectDialog.py
jdDBusDebugger/gui/ConnectFlatpakDialog.py
jdDBusDebugger/gui/ConnectServerDialog.py
jdDBusDebugger/gui/EmitSignalDialog.py
jdDBusDebugger/gui/GenerateScriptDialog.py
jdDBusDebugger/gui/MainWindow.py
jdDBusDebugger/gui/ManageMacrosDialog.py
jdDBusDebugger/gui/MonitorWindow.py
jdDBusDebugger/gui/ServerWindow.py
jdDBusDebugger/gui/SettingsDialog.py
jdDBusDebugger/gui/WelcomeDialog.py
jdDBusDebugger/gui/types_input/ArgumentInput.py
jdDBusDebugger/gui/types_input/ArrayInput.py
jdDBusDebugger/gui/types_input/BrowseButton.py
jdDBusDebugger/gui/types_input/BytearrayInput.py
jdDBusDebugger/gui/types_input/DictInput.py
jdDBusDebugger/gui/types_input/InputHandler.py
jdDBusDebugger/gui/types_input/SingleValueInputDialog.py
jdDBusDebugger/gui/types_input/StructInput.py
jdDBusDebugger/gui/types_input/VariantEdit.py
jdDBusDebugger/gui/types_input/__init__.py
jdDBusDebugger/server_cli/__init__.py
jdDBusDebugger/server_cli/__main__.py
jdDBusDebugger/translations/jdDBusDebugger_ar.qm
jdDBusDebugger/translations/jdDBusDebugger_de.qm
jdDBusDebugger/translations/jdDBusDebugger_nl.qm
jdDBusDebugger/translations/jdDBusDebugger_pt_BR.qm
jdDBusDebugger/types/Connection.py
jdDBusDebugger/types/DBusType.py
jdDBusDebugger/types/DBusValue.py
jdDBusDebugger/types/EnumHelper.py
jdDBusDebugger/types/Interface.py
jdDBusDebugger/types/Macro.py
jdDBusDebugger/types/Method.py
jdDBusDebugger/types/Property.py
jddbusdebugger-4.2.dist-info/licenses/LICENSE
jddbusdebugger-4.2.dist-info/METADATA
jddbusdebugger-4.2.dist-info/WHEEL
jddbusdebugger-4.2.dist-info/entry_points.txt
jddbusdebugger-4.2.dist-info/top_level.txt
jddbusdebugger-4.2.dist-info/RECORD
