Metadata-Version: 2.4
Name: jdDBusDebugger
Version: 4.2
Summary: An advanced D-Bus Debugger
Author-email: JakobDev <jakobdev@gmx.de>
License-Expression: GPL-3.0-only
Project-URL: Source, https://codeberg.org/JakobDev/jdDBusDebugger
Project-URL: Issues, https://codeberg.org/JakobDev/jdDBusDebugger/issues
Project-URL: Translate, https://translate.codeberg.org/projects/jdDBusDebugger
Project-URL: Donation, https://ko-fi.com/jakobdev
Keywords: JakobDev,Linux,DBus
Classifier: Development Status :: 5 - Production/Stable
Classifier: Intended Audience :: Developers
Classifier: Environment :: Other Environment
Classifier: Operating System :: POSIX :: Linux
Classifier: Programming Language :: Python :: 3
Classifier: Programming Language :: Python :: 3.10
Classifier: Programming Language :: Python :: 3.11
Classifier: Programming Language :: Python :: 3 :: Only
Classifier: Programming Language :: Python :: Implementation :: CPython
Requires-Python: >=3.10
License-File: LICENSE
Requires-Dist: PyQt6
Requires-Dist: lxml
Requires-Dist: jeepney
Dynamic: license-file
